MANIFEST.in
requirements.txt
setup.py
twoline_logwatch/__init__.py
twoline_logwatch/cmdline.py
twoline_logwatch/watcher.py
twoline_logwatch.egg-info/PKG-INFO
twoline_logwatch.egg-info/SOURCES.txt
twoline_logwatch.egg-info/dependency_links.txt
twoline_logwatch.egg-info/entry_points.txt
twoline_logwatch.egg-info/requires.txt
twoline_logwatch.egg-info/top_level.txt