Metadata-Version: 1.1
Name: twoline-logwatch
Version: 0.1
Summary: Watch specified folders for logging messages, and display messages using twoline for matches.
Home-page: http://github.com/coddingtonbear/twoline-logwatch
Author: Adam Coddington
Author-email: me@adamcoddington.net
License: UNKNOWN
Platform: UNKNOWN
Classifier: Development Status :: 4 - Beta
Classifier: Intended Audience :: Developers
Classifier: License :: OSI Approved :: MIT License
Classifier: Operating System :: MacOS :: MacOS X
Classifier: Operating System :: Microsoft :: Windows
Classifier: Operating System :: POSIX
